NanStats-0.0.1.dist-info/DESCRIPTION.rst
NanStats-0.0.1.dist-info/METADATA
NanStats-0.0.1.dist-info/RECORD
NanStats-0.0.1.dist-info/WHEEL
NanStats-0.0.1.dist-info/metadata.json
NanStats-0.0.1.dist-info/top_level.txt
nanigans/__init__.py
nanigans/auth.py
nanigans/config.py
nanigans/models.py
nanigans/structures.py
nanigans/utils.py
nanigans/api/__init__.py
nanigans/api/events.py
nanigans/api/facebook.py
nanigans/api/multichannel.py
nanigans/api/publishers.py
nanigans/tests/__init__.py
nanigans/tests/api_tests.py
nanigans/tests/models_tests.py
nanigans/tests/structures_tests.py
nanigans/tests/utils_tests.py
