Metadata-Version: 2.0
Name: NanStats
Version: 0.0.1
Summary: A Python adapter for the Nanigans Reporting API.
Home-page: https://github.com/unique-influence-tech/nanigans-reporting-api
Author: Sean Kennedy
Author-email: UNKNOWN
License: MIT
Keywords: advertising,facebook,data
Platform: UNKNOWN
Classifier: Development Status :: 3 - Alpha
Classifier: Intended Audience :: Developers
Classifier: Topic :: Software Development :: Libraries :: Python Modules
Classifier: License :: OSI Approved :: MIT License
Classifier: Programming Language :: Python :: 2.7
Classifier: Programming Language :: Python :: 3
Classifier: Programming Language :: Python :: 3.3
Classifier: Programming Language :: Python :: 3.4
Classifier: Programming Language :: Python :: 3.5
Requires-Dist: mock
Requires-Dist: requests
